term_matcher/__init__.py
term_matcher/term_matcher.py
term_matcher-0.21.dist-info/LICENSE
term_matcher-0.21.dist-info/METADATA
term_matcher-0.21.dist-info/WHEEL
term_matcher-0.21.dist-info/top_level.txt
term_matcher-0.21.dist-info/RECORD
