Metadata-Version: 2.1
Name: term_matcher
Version: 0.21
Summary: A library for fuzzy matching terms in text with corresponding codes.
Home-page: https://github.com/unai-zulaika/term_matcher
Author: Unai Zulaika
Author-email: unai.zulaika@deusto.es
Keywords: fuzzy matching terms codes
Classifier: Programming Language :: Python :: 3
Classifier: License :: OSI Approved :: MIT License
Classifier: Operating System :: OS Independent
Classifier: Intended Audience :: Developers
Classifier: Topic :: Software Development :: Libraries
Requires-Python: >=3.6
License-File: LICENSE
Requires-Dist: rapidfuzz
Requires-Dist: tqdm
